gitws/__init__.py
gitws/__main__.py
gitws/_basemodel.py
gitws/_cli/__init__.py
gitws/_cli/common.py
gitws/_cli/config.py
gitws/_cli/dep/__init__.py
gitws/_cli/dep/update.py
gitws/_cli/info.py
gitws/_cli/logging.py
gitws/_cli/manifest.py
gitws/_cli/options.py
gitws/_cli/remote.py
gitws/_deptree.py
gitws/_iters.py
gitws/_manifestformatmanager.py
gitws/_pathlock.py
gitws/_stringconverter.py
gitws/_url.py
gitws/_util.py
gitws/_workspacemanager.py
gitws/appconfig.py
gitws/clone.py
gitws/const.py
gitws/datamodel.py
gitws/exceptions.py
gitws/git.py
gitws/gitws.py
gitws/gitwsmanifestformat.py
gitws/manifestfinder.py
gitws/manifestformat.py
gitws/workspace.py
gitws/workspacefinder.py
git_ws-2.0.0.dist-info/COPYING
git_ws-2.0.0.dist-info/COPYING.LESSER
git_ws-2.0.0.dist-info/METADATA
git_ws-2.0.0.dist-info/WHEEL
git_ws-2.0.0.dist-info/entry_points.txt
git_ws-2.0.0.dist-info/RECORD
