Metadata-Version: 2.1
Name: git-ws
Version: 2.0.0
Summary: Git Workspace - Multi Repository Management Tool
License: LGPL-3.0-or-later
Author: c0fec0de
Author-email: c0fec0de@gmail.com
Requires-Python: >=3.8.2,<4.0.0
Classifier: License :: OSI Approved :: GNU Lesser General Public License v3 or later (LGPLv3+)
Classifier: Operating System :: OS Independent
Classifier: Programming Language :: Python :: 3
Classifier: Programming Language :: Python :: 3.9
Classifier: Programming Language :: Python :: 3.10
Classifier: Programming Language :: Python :: 3.11
Classifier: Programming Language :: Python :: 3.12
Requires-Dist: anytree (>=2.8.0,<3.0.0)
Requires-Dist: appdirs (>=1.4.4,<2.0.0)
Requires-Dist: click (>=6.7.0,<9.0.0)
Requires-Dist: flufl-lock (>=6.0,<9.0)
Requires-Dist: importlib-metadata (>=6.8.0,<7.0.0) ; python_version < "3.10"
Requires-Dist: pydantic (>=2.2.0,<3.0.0)
Requires-Dist: pydantic-settings (>=2.0.3,<3.0.0)
Requires-Dist: tomlkit (>=0.11.5,<1.0.0)
